<?xml version="1.0" encoding="utf-8" ?>
<dwsync>
<file name="7N_small.jpg" server="le-timsam.com/www/" local="130756610515129266" remote="130756602600000000" Dst="2" />
<file name="7C-(2)_small.jpg" server="le-timsam.com/www/" local="130756610646781401" remote="130756603200000000" Dst="2" />
<file name="3N_small.jpg" server="le-timsam.com/www/" local="130756611331283615" remote="130756603200000000" Dst="2" />
<file name="2N_small.jpg" server="le-timsam.com/www/" local="130756610097921725" remote="130756603200000000" Dst="2" />
<file name="6n-1_small.jpg" server="le-timsam.com/www/" local="130756610765425312" remote="130756603200000000" Dst="2" />
<file name="4c-1_small.jpg" server="le-timsam.com/www/" local="130756610889132294" remote="130756603200000000" Dst="2" />
<file name="platveget_small.jpg" server="le-timsam.com/www/" local="130756610245537146" remote="130756603200000000" Dst="2" />
<file name="mokpa_small.jpg" server="le-timsam.com/www/" local="130756610397385295" remote="130756603200000000" Dst="2" />
</dwsync>